{"stats":{"minecraft:killed_by":{"minecraft:ghast":1,"minecraft:creeper":2,"minecraft:vindicator":1,"minecraft:blaze":1,"minecraft:zombie":1,"minecraft:player":23,"minecraft:iron_golem":3},"minecraft:custom":{"minecraft:interact_with_crafting_table":191,"minecraft:open_barrel":154,"minecraft:bell_ring":69,"minecraft:leave_game":44,"minecraft:time_since_death":49175,"minecraft:sprint_one_cm":1886747,"minecraft:damage_blocked_by_shield":3726,"minecraft:drop":355,"minecraft:talked_to_villager":26,"minecraft:play_time":844269,"minecraft:deaths":38,"minecraft:jump":10715,"minecraft:walk_on_water_one_cm":112460,"minecraft:interact_with_furnace":76,"minecraft:sleep_in_bed":9,"minecraft:damage_dealt":30862,"minecraft:player_kills":12,"minecraft:crouch_one_cm":55187,"minecraft:interact_with_smithing_table":5,"minecraft:interact_with_smoker":34,"minecraft:horse_one_cm":259545,"minecraft:interact_with_anvil":2,"minecraft:mob_kills":147,"minecraft:inspect_hopper":2,"minecraft:climb_one_cm":5452,"minecraft:walk_one_cm":3228330,"minecraft:raid_win":1,"minecraft:sneak_time":17303,"minecraft:walk_under_water_one_cm":87048,"minecraft:boat_one_cm":565311,"minecraft:interact_with_blast_furnace":3,"minecraft:total_world_time":844269,"minecraft:interact_with_stonecutter":28,"minecraft:time_since_rest":9311,"minecraft:damage_taken":22857,"minecraft:swim_one_cm":157738,"minecraft:fly_one_cm":1514056,"minecraft:open_chest":496,"minecraft:fall_one_cm":330740},"minecraft:dropped":{"minecraft:iron_sword":5,"minecraft:soul_sand":4,"minecraft:porkchop":16,"minecraft:lapis_lazuli":18,"minecraft:cooked_beef":26,"minecraft:baked_potato":28,"minecraft:ender_pearl":1,"minecraft:diamond":3,"minecraft:crafting_table":1,"minecraft:cooked_porkchop":7,"minecraft:crossbow":2,"minecraft:warped_roots":2,"minecraft:lantern":3,"minecraft:rail":4,"soulsweapons:demon_heart":1,"minecraft:flint":1,"minecraft:cobblestone_stairs":17,"minecraft:dirt":43,"minecraft:polished_blackstone_brick_stairs":6,"minecraft:crimson_roots":6,"minecraft:gold_nugget":23,"minecraft:pumpkin_pie":12,"minecraft:sand":2,"minecraft:iron_pickaxe":7,"minecraft:gold_ingot":1,"minecraft:bone":12,"minecraft:sugar_cane":4,"minecraft:iron_nugget":1,"minecraft:cobbled_deepslate":53,"minecraft:twisting_vines":2,"minecraft:wheat":19,"minecraft:rotten_flesh":33,"minecraft:oak_planks":4,"minecraft:cooked_mutton":9,"minecraft:poppy":1,"minecraft:gunpowder":2,"minecraft:spruce_slab":2,"minecraft:arrow":34,"minecraft:beef":25,"minecraft:warped_wart_block":1,"minecraft:oak_leaves":7,"minecraft:netherrack":284,"minecraft:water_bucket":1,"minecraft:stone_hoe":1,"minecraft:golden_boots":1,"minecraft:iron_ingot":2,"minecraft:bread":40,"minecraft:wheat_seeds":100,"minecraft:poisonous_potato":1,"minecraft:iron_helmet":2,"minecraft:oak_fence":4,"minecraft:feather":6,"minecraft:cobblestone":32,"minecraft:spruce_stairs":16,"soulsweapons:holy_greatsword":1,"minecraft:stick":28,"minecraft:spruce_hanging_sign":2,"minecraft:milk_bucket":1,"minecraft:torch":4,"minecraft:fire_charge":3,"minecraft:iron_leggings":7,"minecraft:polished_blackstone_brick_slab":1,"minecraft:iron_axe":4,"minecraft:iron_shovel":5,"minecraft:acacia_planks":7,"minecraft:dandelion":2,"minecraft:redstone":26,"minecraft:nether_brick_slab":1,"minecraft:coarse_dirt":3,"minecraft:iron_boots":5,"minecraft:iron_hoe":3,"minecraft:stripped_oak_log":2,"soulsweapons:kirkhammer":3,"minecraft:nether_bricks":1,"minecraft:shears":1,"minecraft:diamond_sword":1,"minecraft:stone":4,"minecraft:shield":4,"minecraft:spruce_trapdoor":5,"minecraft:spruce_planks":6,"minecraft:iron_chestplate":1,"minecraft:andesite":1,"minecraft:oak_boat":1,"minecraft:oak_sapling":5,"minecraft:spider_eye":1,"minecraft:bow":1,"minecraft:stone_pickaxe":1},"minecraft:killed":{"minecraft:zombified_piglin":7,"minecraft:witch":1,"minecraft:spider":1,"minecraft:skeleton":10,"minecraft:chicken":5,"soulsweapons:evil_forlorn":2,"minecraft:magma_cube":12,"minecraft:pig":9,"minecraft:salmon":6,"minecraft:iron_golem":4,"minecraft:creeper":1,"minecraft:sheep":6,"minecraft:trader_llama":1,"minecraft:pillager":3,"minecraft:zombie":34,"minecraft:donkey":1,"minecraft:ghast":1,"minecraft:blaze":10,"minecraft:cow":19,"minecraft:horse":2,"soulsweapons:withered_demon":3,"minecraft:player":1,"minecraft:villager":3,"minecraft:enderman":3},"minecraft:crafted":{"minecraft:smooth_stone":17,"minecraft:oak_planks":184,"minecraft:barrel":3,"minecraft:cobblestone_slab":20,"minecraft:oak_sign":12,"minecraft:cooked_chicken":7,"soulsweapons:molten_demon_heart":2,"minecraft:stone":129,"minecraft:bookshelf":4,"minecraft:cooked_mutton":22,"minecraft:spruce_pressure_plate":9,"minecraft:dark_oak_door":3,"minecraft:iron_boots":6,"minecraft:chest":4,"minecraft:stone_bricks":31,"minecraft:oak_fence":12,"minecraft:golden_boots":3,"minecraft:smoker":1,"minecraft:oak_slab":6,"minecraft:cooked_porkchop":29,"minecraft:crafting_table":1,"minecraft:spruce_planks":200,"minecraft:acacia_slab":12,"minecraft:iron_helmet":7,"soulsweapons:kirkhammer":1,"minecraft:spruce_door":3,"minecraft:campfire":26,"minecraft:stone_brick_stairs":27,"minecraft:spruce_trapdoor":26,"minecraft:lectern":4,"minecraft:iron_chestplate":6,"minecraft:book":12,"minecraft:paper":36,"minecraft:shield":4,"minecraft:stick":190,"minecraft:iron_ingot":25,"minecraft:iron_pickaxe":7,"minecraft:stone_sword":1,"minecraft:gold_ingot":5,"minecraft:spruce_fence_gate":2,"minecraft:polished_andesite":4,"minecraft:coarse_dirt":56,"minecraft:cobbled_deepslate_slab":6,"ad_astra:iron_rod":4,"grapplemod:doubleupgradeitem":1,"minecraft:stone_shovel":1,"minecraft:stone_brick_wall":23,"minecraft:furnace":1,"minecraft:blast_furnace":2,"soulsweapons:holy_greatsword":1,"minecraft:bone_meal":6,"minecraft:spruce_fence":39,"minecraft:candle":1,"minecraft:flint_and_steel":1,"minecraft:lantern":3,"minecraft:spruce_stairs":24,"minecraft:polished_diorite":4,"minecraft:iron_axe":3,"grapplemod:grapplinghook":2,"minecraft:spruce_slab":30,"minecraft:cobblestone_wall":1,"minecraft:cobbled_deepslate_stairs":20,"minecraft:cooked_beef":40,"grapplemod:baseupgradeitem":1,"minecraft:iron_sword":5,"minecraft:nether_bricks":4,"minecraft:cooked_salmon":7,"minecraft:glowstone":1,"minecraft:air":0,"minecraft:oak_fence_gate":12,"minecraft:oak_stairs":4,"minecraft:iron_leggings":7,"minecraft:stonecutter":1,"minecraft:acacia_planks":12,"minecraft:torch":12},"minecraft:used":{"minecraft:nether_brick_fence":8,"minecraft:iron_shovel":12,"minecraft:spruce_slab":17,"minecraft:oak_sign":10,"minecraft:shield":96,"minecraft:chest":4,"minecraft:iron_sword":674,"minecraft:iron_chestplate":3,"minecraft:soul_sand":9,"minecraft:carrot":7,"minecraft:acacia_sapling":4,"minecraft:azure_bluet":1,"minecraft:stripped_spruce_log":1,"minecraft:spruce_boat":7,"minecraft:lantern":7,"minecraft:warped_nylium":2,"minecraft:iron_helmet":2,"minecraft:stone_brick_stairs":36,"minecraft:stone_bricks":24,"minecraft:spruce_hanging_sign":1,"minecraft:golden_sword":14,"minecraft:bow":13,"minecraft:oak_sapling":1,"minecraft:potato":2,"minecraft:golden_boots":2,"minecraft:spruce_door":6,"minecraft:oak_planks":2,"minecraft:ender_pearl":1,"minecraft:blackstone":2,"minecraft:sugar_cane":18,"minecraft:oak_leaves":31,"minecraft:blast_furnace":2,"minecraft:stone_brick_wall":23,"minecraft:cobbled_deepslate_stairs":25,"minecraft:shears":33,"soulsweapons:infused_blackstone":1,"minecraft:bread":52,"minecraft:lectern":8,"minecraft:gravel":9,"minecraft:lilac":2,"minecraft:diamond_sword":4,"minecraft:smithing_table":2,"minecraft:andesite":1,"minecraft:oak_fence":15,"minecraft:coarse_dirt":58,"minecraft:golden_pickaxe":3,"minecraft:oak_boat":2,"minecraft:bone_meal":6,"minecraft:flint_and_steel":31,"minecraft:stone_shovel":132,"minecraft:spruce_planks":21,"minecraft:cooked_salmon":5,"minecraft:stone_hoe":1,"minecraft:cooked_chicken":3,"minecraft:netherrack":341,"minecraft:torch":7,"minecraft:dirt":220,"minecraft:white_carpet":2,"minecraft:spruce_stairs":34,"minecraft:cobblestone_wall":1,"minecraft:spruce_fence":40,"minecraft:oak_fence_gate":15,"minecraft:polished_diorite":5,"minecraft:iron_hoe":1,"soulsweapons:kirkhammer":142,"minecraft:iron_axe":324,"minecraft:oak_stairs":7,"minecraft:iron_boots":1,"minecraft:barrel":3,"minecraft:glowstone":1,"minecraft:basalt":10,"minecraft:cooked_beef":56,"minecraft:cobbled_deepslate":46,"minecraft:acacia_planks":1,"minecraft:iron_leggings":6,"minecraft:pointed_dripstone":7,"minecraft:wheat_seeds":22,"minecraft:cooked_mutton":21,"minecraft:acacia_boat":5,"minecraft:cobblestone_stairs":11,"grapplemod:grapplinghook":2,"minecraft:polished_andesite":4,"minecraft:baked_potato":3,"minecraft:cobblestone_slab":28,"minecraft:stonecutter":2,"minecraft:spruce_fence_gate":2,"minecraft:polished_blackstone_bricks":9,"minecraft:rail":1,"minecraft:crafting_table":6,"minecraft:oak_slab":2,"minecraft:campfire":29,"minecraft:spruce_log":9,"minecraft:dark_oak_door":6,"minecraft:smoker":1,"minecraft:oak_log":11,"soulsweapons:holy_greatsword":6,"minecraft:diamond_pickaxe":6,"minecraft:cornflower":1,"minecraft:apple":1,"minecraft:oxeye_daisy":1,"minecraft:iron_pickaxe":1571,"minecraft:spruce_pressure_plate":12,"minecraft:spruce_trapdoor":53,"minecraft:cobblestone":118,"minecraft:cobbled_deepslate_slab":6,"minecraft:cooked_porkchop":38,"minecraft:glass_pane":3,"minecraft:stripped_oak_log":6,"minecraft:dandelion":3,"minecraft:candle":1,"minecraft:smooth_stone":3},"minecraft:broken":{"minecraft:iron_shovel":1,"minecraft:iron_sword":1,"minecraft:stone_shovel":1,"minecraft:iron_pickaxe":4,"minecraft:iron_helmet":2},"minecraft:mined":{"minecraft:spruce_planks":15,"minecraft:farmland":5,"minecraft:cobbled_deepslate_stairs":5,"minecraft:cobblestone_stairs":3,"minecraft:obsidian":1,"minecraft:spruce_trapdoor":22,"minecraft:acacia_log":39,"minecraft:grass_block":153,"minecraft:stone_brick_wall":15,"minecraft:cracked_polished_blackstone_bricks":5,"minecraft:polished_diorite":1,"minecraft:polished_blackstone_brick_slab":1,"minecraft:oxeye_daisy":1,"minecraft:gilded_blackstone":1,"minecraft:smooth_stone":3,"minecraft:polished_blackstone_bricks":14,"minecraft:magma_block":4,"minecraft:glowstone":7,"minecraft:iron_ore":28,"minecraft:fire":25,"minecraft:cobbled_deepslate":25,"minecraft:deepslate_lapis_ore":3,"minecraft:azure_bluet":1,"minecraft:twisting_vines":3,"minecraft:pointed_dripstone":9,"minecraft:oak_stairs":3,"minecraft:spruce_pressure_plate":3,"minecraft:spruce_slab":8,"minecraft:tripwire":1,"minecraft:deepslate_redstone_ore":8,"minecraft:blackstone":11,"minecraft:torch":5,"minecraft:nether_brick_slab":1,"minecraft:nether_quartz_ore":116,"minecraft:cobblestone":131,"minecraft:oak_planks":2,"minecraft:sugar_cane":61,"minecraft:wall_torch":1,"minecraft:deepslate_copper_ore":2,"minecraft:white_terracotta":26,"minecraft:seagrass":1,"minecraft:chain":4,"soulsweapons:cracked_infused_blackstone":1,"minecraft:nether_wart_block":3,"minecraft:dark_oak_door":4,"minecraft:wheat":20,"minecraft:lilac":2,"minecraft:stone_brick_stairs":8,"minecraft:yellow_stained_glass_pane":2,"minecraft:oak_log":42,"minecraft:oak_fence_gate":3,"minecraft:dirt":147,"minecraft:crimson_planks":1,"minecraft:wither_skeleton_skull":1,"minecraft:stonecutter":1,"minecraft:netherrack":408,"minecraft:oak_leaves":74,"minecraft:deepslate":78,"minecraft:nether_gold_ore":22,"minecraft:diamond_ore":1,"minecraft:tuff":9,"minecraft:mossy_cobblestone":2,"minecraft:deepslate_diamond_ore":4,"soulsweapons:infused_blackstone":5,"minecraft:nether_bricks":42,"minecraft:spruce_fence":5,"minecraft:crimson_roots":3,"minecraft:weeping_vines":2,"minecraft:spruce_leaves":9,"minecraft:cracked_nether_bricks":1,"minecraft:redstone_ore":6,"minecraft:furnace":1,"minecraft:black_glazed_terracotta":11,"minecraft:andesite":6,"minecraft:stripped_spruce_log":7,"minecraft:gold_block":1,"minecraft:nether_brick_fence":13,"minecraft:potatoes":8,"minecraft:shroomlight":1,"minecraft:cobblestone_slab":30,"minecraft:rail":4,"minecraft:lantern":6,"minecraft:stripped_oak_log":2,"minecraft:stone":327,"minecraft:smithing_table":1,"minecraft:acacia_leaves":17,"minecraft:glass_pane":2,"minecraft:chiseled_nether_bricks":1,"minecraft:basalt":22,"minecraft:dandelion":5,"minecraft:spruce_door":3,"minecraft:oak_fence":6,"minecraft:crafting_table":3,"minecraft:cornflower":2,"minecraft:short_grass":133,"minecraft:rose_bush":3,"minecraft:campfire":14,"minecraft:lectern":4,"minecraft:copper_ore":15,"minecraft:tall_grass":23,"minecraft:lapis_ore":17,"minecraft:deepslate_gold_ore":5,"minecraft:polished_blackstone_brick_stairs":2,"minecraft:diorite":15,"minecraft:warped_wart_block":3,"minecraft:spruce_stairs":16,"minecraft:coarse_dirt":2,"minecraft:white_carpet":1,"minecraft:spruce_log":61,"minecraft:bee_nest":1,"minecraft:yellow_bed":1,"minecraft:coal_ore":32,"minecraft:gravel":21,"minecraft:dripstone_block":6,"minecraft:cobweb":2,"minecraft:spruce_fence_gate":3,"minecraft:stone_bricks":2},"minecraft:picked_up":{"minecraft:iron_chestplate":16,"minecraft:wheat":53,"minecraft:nether_brick_fence":20,"minecraft:lead":2,"minecraft:smithing_table":3,"minecraft:diamond_sword":2,"minecraft:oak_stairs":4,"minecraft:nether_brick":20,"minecraft:stone_brick_stairs":9,"minecraft:crimson_planks":1,"minecraft:golden_sword":1,"minecraft:polished_blackstone_brick_stairs":6,"minecraft:string":6,"minecraft:raw_copper":54,"minecraft:cooked_salmon":12,"minecraft:iron_leggings":25,"minecraft:shroomlight":1,"minecraft:smooth_stone":3,"minecraft:gold_nugget":98,"minecraft:cobbled_deepslate":146,"minecraft:black_glazed_terracotta":10,"minecraft:spruce_planks":58,"grapplemod:grapplinghook":2,"minecraft:rose_bush":3,"minecraft:cobblestone_slab":28,"minecraft:iron_pickaxe":23,"minecraft:iron_boots":14,"minecraft:furnace":3,"minecraft:dark_oak_door":5,"minecraft:polished_blackstone_brick_slab":1,"minecraft:spruce_pressure_plate":3,"minecraft:stick":59,"minecraft:oak_fence":7,"minecraft:torch":24,"minecraft:acacia_log":45,"minecraft:spruce_stairs":32,"minecraft:porkchop":27,"minecraft:pointed_dripstone":20,"minecraft:diorite":15,"minecraft:chiseled_nether_bricks":1,"minecraft:stone_sword":1,"minecraft:rotten_flesh":38,"minecraft:white_terracotta":22,"minecraft:blaze_rod":7,"minecraft:cobblestone":865,"minecraft:magma_block":4,"minecraft:cooked_beef":94,"minecraft:feather":7,"minecraft:lilac":2,"minecraft:magma_cream":3,"minecraft:birch_slab":3,"minecraft:water_bucket":1,"minecraft:andesite":5,"minecraft:potato":6,"minecraft:flint":6,"minecraft:tuff":7,"minecraft:acacia_boat":5,"minecraft:wither_skeleton_skull":1,"minecraft:lapis_lazuli":151,"minecraft:dirt":462,"minecraft:lantern":10,"minecraft:twisting_vines":2,"minecraft:bone":12,"minecraft:acacia_planks":22,"minecraft:bow":8,"minecraft:stonecutter":1,"minecraft:wheat_seeds":229,"minecraft:raw_gold":5,"minecraft:glowstone_dust":38,"minecraft:stone_hoe":1,"minecraft:oak_planks":29,"minecraft:honeycomb":3,"minecraft:chiseled_polished_blackstone":2,"minecraft:cooked_porkchop":36,"minecraft:warped_wart_block":1,"minecraft:poisonous_potato":1,"minecraft:sand":4,"minecraft:stripped_spruce_log":7,"minecraft:spectral_arrow":11,"minecraft:mossy_cobblestone":2,"minecraft:iron_hoe":3,"minecraft:spruce_fence_gate":2,"minecraft:diamond":7,"minecraft:spruce_boat":7,"minecraft:cracked_polished_blackstone_bricks":12,"minecraft:crossbow":6,"minecraft:spruce_sign":1,"minecraft:bread":155,"minecraft:oak_sapling":6,"minecraft:netherrack":657,"minecraft:oak_leaves":40,"minecraft:crimson_roots":6,"minecraft:coarse_dirt":5,"minecraft:charcoal":26,"minecraft:crafting_table":7,"minecraft:azure_bluet":1,"minecraft:chicken":3,"minecraft:golden_pickaxe":2,"minecraft:brown_mushroom":1,"minecraft:stone_brick_wall":9,"minecraft:gold_block":1,"minecraft:diamond_horse_armor":1,"minecraft:chain":2,"soulsweapons:cracked_infused_blackstone":6,"minecraft:shield":25,"minecraft:cornflower":2,"soulsweapons:demon_heart":3,"minecraft:iron_axe":14,"minecraft:flint_and_steel":3,"minecraft:white_carpet":2,"minecraft:iron_shovel":15,"minecraft:blackstone":25,"soulsweapons:infused_blackstone":6,"minecraft:beef":51,"minecraft:oak_boat":4,"minecraft:poppy":5,"minecraft:spruce_slab":11,"minecraft:lectern":4,"minecraft:sugar_cane":86,"minecraft:chest":1,"minecraft:spruce_trapdoor":32,"minecraft:raw_iron":25,"minecraft:stone":57,"minecraft:spruce_fence":6,"minecraft:fire_charge":3,"minecraft:polished_blackstone_bricks":31,"minecraft:redstone":89,"minecraft:iron_horse_armor":1,"minecraft:arrow":43,"minecraft:weeping_vines":2,"minecraft:stone_shovel":2,"minecraft:pumpkin_pie":12,"minecraft:nether_bricks":35,"minecraft:shears":2,"minecraft:saddle":1,"minecraft:gold_ingot":1,"minecraft:mutton":18,"minecraft:rail":9,"minecraft:white_wool":16,"minecraft:oxeye_daisy":1,"minecraft:stripped_oak_log":2,"minecraft:basalt":22,"minecraft:salmon":6,"minecraft:leather":23,"minecraft:oak_log":61,"minecraft:lily_pad":4,"minecraft:golden_boots":10,"minecraft:nether_wart_block":2,"minecraft:cobbled_deepslate_stairs":5,"minecraft:gunpowder":5,"minecraft:cobblestone_stairs":20,"minecraft:cooked_mutton":20,"minecraft:stone_bricks":2,"minecraft:iron_ingot":184,"minecraft:oak_fence_gate":3,"minecraft:stone_pickaxe":1,"minecraft:glass_bottle":1,"minecraft:iron_sword":17,"minecraft:acacia_sapling":4,"minecraft:soul_sand":17,"minecraft:milk_bucket":1,"soulsweapons:holy_greatsword":3,"minecraft:quartz":161,"minecraft:cracked_nether_bricks":1,"minecraft:dandelion":9,"minecraft:dripstone_block":4,"minecraft:gravel":59,"minecraft:spruce_log":59,"minecraft:nether_brick_slab":1,"minecraft:spruce_door":3,"minecraft:spider_eye":2,"soulsweapons:kirkhammer":5,"minecraft:polished_diorite":1,"minecraft:short_grass":4,"minecraft:iron_helmet":11,"minecraft:warped_roots":2,"minecraft:baked_potato":31,"minecraft:warped_nylium":2,"minecraft:coal":33,"minecraft:ender_pearl":4}},"DataVersion":3700}